LICENSE
MANIFEST.in
README.rst
setup.cfg
setup.py
flashtext/__init__.py
flashtext/keyword.py
flashtext.egg-info/PKG-INFO
flashtext.egg-info/SOURCES.txt
flashtext.egg-info/dependency_links.txt
flashtext.egg-info/top_level.txt
test/__init__.py
test/test_dictionary_loading.py
test/test_extractor.py
test/test_file_load.py
test/test_kp_exceptions.py
test/test_kp_extract_span.py
test/test_kp_get_all_keywords.py
test/test_kp_len.py
test/test_kp_term_in_kp.py
test/test_loading_keyword_list.py
test/test_remove_keywords.py
test/test_replacer.py