Metadata-Version: 1.1
Name: flashtext
Version: 2.6
Summary: Extract/Replaces keywords in sentences.
Home-page: http://github.com/vi3k6i5/flashtext
Author: Vikash Singh
Author-email: vikash.duliajan@gmail.com
License: UNKNOWN
Platform: any
Classifier: Programming Language :: Python
Classifier: Programming Language :: Python :: 2.7
Classifier: Programming Language :: Python :: 3.5
Classifier: Programming Language :: Python :: 3.6
Classifier: Operating System :: OS Independent
Classifier: Intended Audience :: Developers
Classifier: License :: OSI Approved :: MIT License
